howmuch/HowMuch.py
howmuch/__init__.py
howmuch-0.1.1.dist-info/LICENSE
howmuch-0.1.1.dist-info/METADATA
howmuch-0.1.1.dist-info/WHEEL
howmuch-0.1.1.dist-info/entry_points.txt
howmuch-0.1.1.dist-info/top_level.txt
howmuch-0.1.1.dist-info/RECORD
