Metadata-Version: 2.1
Name: howmuch
Version: 0.1.1
Summary: A simple disk space analyzer for *.ckpt & *.safetensors file extensions
Home-page: https://github.com/1e-2/HowMuch
Author: idlebg
Author-email: di@ffusion.ai
Classifier: Programming Language :: Python :: 3
Classifier: License :: OSI Approved :: MIT License
Classifier: Operating System :: OS Independent
License-File: LICENSE
Requires-Dist: psutil
Requires-Dist: tqdm
Requires-Dist: matplotlib
